audiodiffusion/__init__.py
audiodiffusion/audio_encoder.py
audiodiffusion/mel.py
audiodiffusion/pipeline_audio_diffusion.py
audiodiffusion/utils.py
audiodiffusion-1.5.7.dist-info/LICENSE
audiodiffusion-1.5.7.dist-info/METADATA
audiodiffusion-1.5.7.dist-info/WHEEL
audiodiffusion-1.5.7.dist-info/top_level.txt
audiodiffusion-1.5.7.dist-info/RECORD
