Metadata-Version: 2.1
Name: audiodiffusion
Version: 1.5.7
Summary: Generate Mel spectrogram dataset from directory of audio files.
License: GPL3
Classifier: Programming Language :: Python :: 3
License-File: LICENSE
Requires-Dist: torch
Requires-Dist: numpy
Requires-Dist: Pillow
Requires-Dist: diffusers >=0.12.0
Requires-Dist: librosa
Requires-Dist: datasets >=2.9.0
Requires-Dist: accelerate
